alc_attacks/__init__.py
alc_attacks/best_row_match/__init__.py
alc_attacks/best_row_match/brm_attack.py
alc_attacks/best_row_match/matching_routines.py
alc_attacks/best_row_match/run_brm_attack.py
alc_attacks/best_row_match/temp.py
alc_attacks-1.0.5.dist-info/licenses/LICENSE
alc_attacks-1.0.5.dist-info/METADATA
alc_attacks-1.0.5.dist-info/WHEEL
alc_attacks-1.0.5.dist-info/top_level.txt
alc_attacks-1.0.5.dist-info/RECORD
